s3tl/__init__.py
s3tl/core.py
s3tl/extract.py
s3tl/transform.py
s3tl-0.0.1.dist-info/LICENSE
s3tl-0.0.1.dist-info/METADATA
s3tl-0.0.1.dist-info/WHEEL
s3tl-0.0.1.dist-info/top_level.txt
s3tl-0.0.1.dist-info/RECORD
