Metadata-Version: 2.1
Name: s3tl
Version: 0.0.1
Summary: Framework for building ETLs against AWS S3
Home-page: https://github.com/tlovely/s3tl
Author: Tyler Lovely
Author-email: tyler.n.lovely@gmail.com
License: UNKNOWN
Platform: UNKNOWN
Classifier: Development Status :: 3 - Alpha
Classifier: Intended Audience :: Developers
Classifier: License :: OSI Approved :: MIT License
Classifier: Programming Language :: Python :: 3
Classifier: Programming Language :: Python :: 3.6
Classifier: Programming Language :: Python :: 3.7
Classifier: Programming Language :: Python :: 3.8
Classifier: Programming Language :: Python :: 3.9
Classifier: Programming Language :: Python :: 3 :: Only
Requires-Python: >=3.6, <4
Requires-Dist: aiofiles (<1,>=0.6.0)
Requires-Dist: aiobotocore (<2,>=1.2.1)
Requires-Dist: toolz
